pytai/__init__.py
pytai/__main__.py
pytai/application.py
pytai/common.py
pytai/model.py
pytai/utils.py
pytai/kaitai/__init__.py
pytai/kaitai/kaitaistruct.py
pytai/kaitai/formats/README.md
pytai/kaitai/formats/__init__.py
pytai/kaitai/formats/aix_utmp.py
pytai/kaitai/formats/allegro_dat.py
pytai/kaitai/formats/amlogic_emmc_partitions.py
pytai/kaitai/formats/andes_firmware.py
pytai/kaitai/formats/android_bootldr_asus.py
pytai/kaitai/formats/android_bootldr_huawei.py
pytai/kaitai/formats/android_bootldr_qcom.py
pytai/kaitai/formats/android_dto.py
pytai/kaitai/formats/android_img.py
pytai/kaitai/formats/android_nanoapp_header.py
pytai/kaitai/formats/android_opengl_shaders_cache.py
pytai/kaitai/formats/android_sparse.py
pytai/kaitai/formats/android_super.py
pytai/kaitai/formats/apm_partition_table.py
pytai/kaitai/formats/apple_single_double.py
pytai/kaitai/formats/asn1_der.py
pytai/kaitai/formats/au.py
pytai/kaitai/formats/avantes_roh60.py
pytai/kaitai/formats/avi.py
pytai/kaitai/formats/bcd.py
pytai/kaitai/formats/bitcoin_transaction.py
pytai/kaitai/formats/blender_blend.py
pytai/kaitai/formats/bmp.py
pytai/kaitai/formats/bson.py
pytai/kaitai/formats/btrfs_stream.py
pytai/kaitai/formats/bytes_with_io.py
pytai/kaitai/formats/chrome_pak.py
pytai/kaitai/formats/code_6502.py
pytai/kaitai/formats/compressed_resource.py
pytai/kaitai/formats/cpio_old_le.py
pytai/kaitai/formats/cramfs.py
pytai/kaitai/formats/creative_voice_file.py
pytai/kaitai/formats/dbf.py
pytai/kaitai/formats/dcmp_0.py
pytai/kaitai/formats/dcmp_1.py
pytai/kaitai/formats/dcmp_2.py
pytai/kaitai/formats/dcmp_variable_length_integer.py
pytai/kaitai/formats/dex.py
pytai/kaitai/formats/dicom.py
pytai/kaitai/formats/dime_message.py
pytai/kaitai/formats/dns_packet.py
pytai/kaitai/formats/doom_wad.py
pytai/kaitai/formats/dos_datetime.py
pytai/kaitai/formats/dos_mz.py
pytai/kaitai/formats/ds_store.py
pytai/kaitai/formats/dtb.py
pytai/kaitai/formats/dune_2_pak.py
pytai/kaitai/formats/edid.py
pytai_hex-0.2.9.dist-info/LICENSE
pytai_hex-0.2.9.dist-info/METADATA
pytai_hex-0.2.9.dist-info/WHEEL
pytai_hex-0.2.9.dist-info/entry_points.txt
pytai_hex-0.2.9.dist-info/top_level.txt
pytai_hex-0.2.9.dist-info/zip-safe
pytai_hex-0.2.9.dist-info/RECORD
