Metadata-Version: 2.1
Name: pytai-hex
Version: 0.2.9
Summary: Kaitai Struct: Visualizer and Hex Viewer GUI in Python
Author: Dvd848
License: MIT
Project-URL: Homepage, https://github.com/Dvd848/pytai
Keywords: pytai,python,kaitai,gui
Classifier: Development Status :: 4 - Beta
Classifier: Environment :: Other Environment
Classifier: Intended Audience :: Developers
Classifier: License :: OSI Approved
Classifier: License :: OSI Approved :: MIT License
Classifier: Operating System :: OS Independent
Classifier: Programming Language :: Python
Classifier: Programming Language :: Python :: 3
Classifier: Programming Language :: Python :: 3 :: Only
Requires-Python: >=3.8
License-File: LICENSE
Requires-Dist: kaitaistruct>=0.9
